buildbot_console_view/VERSION
buildbot_console_view/__init__.py
buildbot_console_view/static/scripts.js
buildbot_console_view/static/styles.css
buildbot_console_view-4.3.0.dist-info/METADATA
buildbot_console_view-4.3.0.dist-info/WHEEL
buildbot_console_view-4.3.0.dist-info/entry_points.txt
buildbot_console_view-4.3.0.dist-info/top_level.txt
buildbot_console_view-4.3.0.dist-info/RECORD
