Metadata-Version: 2.1
Name: buildbot-console-view
Version: 4.3.0
Summary: Buildbot Console View plugin
Home-page: http://buildbot.net/
Author: Pierre Tardy
Author-email: tardyp@gmail.com
Classifier: License :: OSI Approved :: GNU General Public License v2 (GPLv2)
